derace/__init__.py
derace/debug_trace.py
derace-0.1.0.dist-info/METADATA
derace-0.1.0.dist-info/WHEEL
derace-0.1.0.dist-info/RECORD
